ezpubsub/__init__.py
ezpubsub/py.typed
ezpubsub/signal.py
ezpubsub-0.3.0.dist-info/WHEEL
ezpubsub-0.3.0.dist-info/METADATA
ezpubsub-0.3.0.dist-info/RECORD
