Metadata-Version: 2.3
Name: ezpubsub
Version: 0.3.0
Summary: An ultra simple, modern pub/sub library and blinker alternative for Python
Keywords: python,pubsub,publish-subscribe,typed,thread-safe,event-driven,events
Author: Edward Jazzhands
Author-email: Edward Jazzhands <ed.jazzhands@gmail.com>
License: MIT
Classifier: Development Status :: 3 - Alpha
Classifier: License :: OSI Approved :: MIT License
Classifier: Operating System :: OS Independent
Classifier: Programming Language :: Python
Classifier: Programming Language :: Python :: 3.10
Classifier: Programming Language :: Python :: 3.11
Classifier: Programming Language :: Python :: 3.12
Classifier: Programming Language :: Python :: 3.13
Classifier: Programming Language :: Python :: 3 :: Only
Requires-Python: >=3.9
Project-URL: Changelog, https://github.com/edward-jazzhands/ezpubsub/blob/master/CHANGELOG.md
Project-URL: Repository, https://github.com/edward-jazzhands/ezpubsub
